ipynao/__init__.py
ipynao/_frontend.py
ipynao/_version.py
ipynao/nao_robot.py
ipynao/labextension/build_log.json
ipynao/labextension/package.json
ipynao/labextension/static/lib_index_js.d91068130eddfbfbb881.js
ipynao/labextension/static/lib_index_js.d91068130eddfbfbb881.js.map
ipynao/labextension/static/lib_plugin_js.47728bba116b5e19b216.js
ipynao/labextension/static/lib_plugin_js.47728bba116b5e19b216.js.map
ipynao/labextension/static/lib_widget_js.51b2bf6a918d6fe3f81b.js
ipynao/labextension/static/lib_widget_js.51b2bf6a918d6fe3f81b.js.map
ipynao/labextension/static/remoteEntry.497bfbe551d63a9e7793.js
ipynao/labextension/static/remoteEntry.497bfbe551d63a9e7793.js.map
ipynao/labextension/static/style.js
ipynao/labextension/static/vendors-node_modules_nao-socket_io_index_js.ff3aadb260c5cad63e59.js
ipynao/labextension/static/vendors-node_modules_nao-socket_io_index_js.ff3aadb260c5cad63e59.js.map
ipynao/nbextension/extension.js
ipynao/nbextension/index.js
ipynao/nbextension/index.js.LICENSE.txt
ipynao/nbextension/index.js.map
ipynao/tests/__init__.py
ipynao/tests/conftest.py
ipynao/tests/test_example.py
ipynao/tests/test_nbextension_path.py
ipynao-0.8.9.data/data/share/jupyter/labextensions/ipynao/build_log.json
ipynao-0.8.9.data/data/share/jupyter/labextensions/ipynao/package.json
ipynao-0.8.9.data/data/share/jupyter/labextensions/ipynao/static/lib_index_js.d91068130eddfbfbb881.js
ipynao-0.8.9.data/data/share/jupyter/labextensions/ipynao/static/lib_index_js.d91068130eddfbfbb881.js.map
ipynao-0.8.9.data/data/share/jupyter/labextensions/ipynao/static/lib_plugin_js.47728bba116b5e19b216.js
ipynao-0.8.9.data/data/share/jupyter/labextensions/ipynao/static/lib_plugin_js.47728bba116b5e19b216.js.map
ipynao-0.8.9.data/data/share/jupyter/labextensions/ipynao/static/lib_widget_js.51b2bf6a918d6fe3f81b.js
ipynao-0.8.9.data/data/share/jupyter/labextensions/ipynao/static/lib_widget_js.51b2bf6a918d6fe3f81b.js.map
ipynao-0.8.9.dist-info/METADATA
ipynao-0.8.9.dist-info/WHEEL
ipynao-0.8.9.dist-info/licenses/LICENSE.txt
ipynao-0.8.9.dist-info/RECORD
